README.md
setup.py
yandex_parser/__init__.py
yandex_parser/exceptions.py
yandex_parser/yandex.py
yandex_parser/yandex_debug.py
yandex_parser.egg-info/.gitignore
yandex_parser.egg-info/PKG-INFO
yandex_parser.egg-info/SOURCES.txt
yandex_parser.egg-info/dependency_links.txt
yandex_parser.egg-info/requires.txt
yandex_parser.egg-info/top_level.txt