Metadata-Version: 1.1
Name: yandex-parser
Version: 0.0.193
Summary: Parse html content of Yandex
Home-page: https://github.com/KokocGroup/yandex-parser
Author: UNKNOWN
Author-email: d.borisov@dev.kokoc.com
License: UNKNOWN
Download-URL: https://github.com/KokocGroup/yandex-parser/tarball/v0.0.193
Platform: UNKNOWN
